{
  "id": "b005e617-177b-44be-b453-b167acb84d33",
  "url": "https://allgovernmentjobs.in/midhani-recruitment-2025-walk-in-interview-for-50-assistant-posts/34224",
  "title": "Assistant Level-4 & Level-2",
  "organization": "Mishra Dhatu Nigam Limited",
  "department": null,
  "location": "Telangana",
  "venue": null,
  "positions": [
    {
      "title": "Assistant Level-4 & Level-2",
      "vacancies": 50,
      "qualification": "Diploma in Electrical, Mechanical Engineering, 10th pass, ITI"
    }
  ],
  "totalPosts": 50,
  "qualification": "details, age limit, selection process, application fee, salary, and how to apply for these posts before the deadline",
  "salary": "₹29,800",
  "applicationStartDate": "2025-08-21",
  "lastDate": "2025-09-17",
  "postedDate": "2025-08-22T14:02:29.613Z",
  "links": {
    "official": null,
    "notification": null,
    "applicationForm": "https://files.allgovernmentjobs.in/public/2025/08/1755836585d290652f8d5fae8ea0982d25b8c3210334922dfe.pdf",
    "sourceUrl": "https://allgovernmentjobs.in/midhani-recruitment-2025-walk-in-interview-for-50-assistant-posts/34224",
    "applicationFormR2": "https://pub-3e5281bc67d445b2b6cba74cdfca7241.r2.dev/b005e617-177b-44be-b453-b167acb84d33_form.pdf",
    "applicationFormLocal": "https://pub-3e5281bc67d445b2b6cba74cdfca7241.r2.dev/b005e617-177b-44be-b453-b167acb84d33_form.pdf"
  },
  "metadata": {
    "scrapedAt": "2025-08-22T14:02:29.613Z",
    "processedAt": "2025-08-22T14:05:19.680Z"
  },
  "rawContent": {
    "title": "MIDHANI Recruitment 2025 - Walk-in interview for 50 Assistant Posts",
    "url": "https://allgovernmentjobs.in/midhani-recruitment-2025-walk-in-interview-for-50-assistant-posts/34224",
    "extractedAt": "2025-08-22T14:02:29.604Z",
    "content": {
      "fullText": " Join on Telegram\n  All Government Jobs\nHome\nLatest Govt Jobs\nResults\nQualifications\nOrganizations\nAbout Us\nContact Us\nRegister\nLogin\nHome > Midhani Recruitment > MIDHANI Recruitment 2025 - Walk-in interview for 50 Assistant Posts\n\n\nMIDHANI Recruitment 2025 - Walk-in interview for 50 Assistant Posts\nHarshitha / All Government Jobs / Aug 22, 2025, 09:51 IST\n Mishtra Dhatu Nigam Limited\n 50 Jobs |  Posted On : 22-Aug-2025 |  Telangana |  Salary : 29,800 to 32,640\n\n\n\n\nFOLLOW\n\nThe Mishra Dhatu Nigam Limited (MIDHANI) has officially released the notification to fill the vacancies of 50 Assistant Posts. Interested and eligible candidates can use this opportunity to apply for these posts before the last date of application. Candidates who have completed their Diploma in Electrical, Mechanical Engineering, 10th, and ITI can apply for the MIDHANI Recruitment 2025. The interested applicants can attend the walk-in interview. Here we have mentioned the education details, age limit, selection process, application fee, salary, and how to apply for these posts before the deadline. The application dates have already begun.\n\n\n\n\nIf you are more interested in Government Jobs, candidates can also apply for jobs in Telangana.\n\nMIDHANI Recruitment 2025 Eligibility Criteria:\nName of the Posts\tVacancies\tEducation\nAssistant Level-4 & Level-2\t50\tDiploma in Electrical, Mechanical Engineering, 10th pass, ITI\n\nMIDHANI Recruitment 2025 Age Limit:\n\nThe minimum age limit: 18 Years.\nThe maximum age limit: 35 Years.\nAge relaxation is based on the Organisation's norms.\n\nMIDHANI Recruitment 2025 Selection Process:\n\nThe selection process is based on the interview.\n\nMIDHANI Recruitment 2025 Application Fee:\n\nThere is no application fee.\n\nMIDHANI Recruitment 2025 Pay Scale:\n\nThe minimum salary: Rs. 29,800/- per month.\nThe maximum salary: Rs. 32.640/- per month.\nHow to Apply for the MIDHANI Recruitment 2025:\nGo to the official website.\nVisit the MIDHANI Recruitment 2025 notification.\nRead the instructions carefully and check the eligiblity criteria.\nIf you are eligible.\nGather all the required documents.\nCarry all the documents to the interview.\nAttend the interview at the mentioned address.\n\nAddress:\n\nMIDHANI Corporate Office Auditorium, Kanchanbagh, Hyderabad – 500 058.\n\nImportant Dates:\n\nStarting date\t21-08-2025\nClosing date\t17-09-2025\n\n \n\nOfficial Notification\tClick Here\nJoin Whatsapp Group\tJoin Now\nJoin on Telegram\tJoin Now\n JOIN WHATSAPP GROUP JOIN ON TELEGRAM\nRelated Notifications\nBoard\tPost Name\tVacancies\tDetails\nIndian Bank\tAttender Jobs\n\nPosted on - 22 Aug 2025\n\n\t\n01\n\tVIEW / APPLY\nRRB\tProject Engineer Jobs\n\nPosted on - 22 Aug 2025\n\n\t\n04\n\tVIEW / APPLY\nNHM\tTherapeutic , Multi Purpose Hospital Worker, Consultant, attender Jobs\n\nPosted on - 22 Aug 2025\n\n\t\n09\n\tVIEW / APPLY\nIntelligence Bureau\tJunior Intelligence Officer Grade-II Jobs\n\nPosted on - 22 Aug 2025\n\n\t\n394\n\tVIEW / APPLY\nUCIL\tManagement Trainee, Diploma Trainee, Graduate Operational Trainee Jobs\n\nPosted on - 22 Aug 2025\n\n\t\n99\n\tVIEW / APPLY\nWCR\tApprentice Jobs\n\nPosted on - 22 Aug 2025\n\n\t\n2865\n\tVIEW / APPLY\nCCI\tSecurity Guard Jobs\n\nPosted on - 22 Aug 2025\n\n\t\n01\n\tVIEW / APPLY\nISRO\tGraduate Apprentice Jobs\n\nPosted on - 22 Aug 2025\n\n\t\n96\n\tVIEW / APPLY\nNHM\tNurse, Pharmacist, Lab Technician, Support Staff, Counsellor Jobs\n\nPosted on - 22 Aug 2025\n\n\t\n33\n\tVIEW / APPLY\nSVNIT\tJunior Research Fellow Jobs\n\nPosted on - 22 Aug 2025\n\n\t\n01\n\tVIEW / APPLY\n SEARCH\n SUBSCRIBE JOIN WHATSAPP GROUP JOIN ON TELEGRAM LIKE US ON FACEBOOK FOLLOW ON TWITTER SUBSCRIBE ON YOUTUBE\nRecommended Jobs\nGovernment Jobs\nEngineering Jobs\nMedical Jobs\nAny Degree Jobs\nNursing Jobs\nCivil Engineering Jobs\n10th Pass Govt Job\nPharmacist Vacancy\nRecent Notifications\nIndian Bank Recruitment 2025 - Apply Offline for Attender Post\nMRVC Recruitment 2025 - Apply Offline for 04 Project Engineer Posts\nIFGTB Recruitment 2025 - Apply Online for 13 Research Associate and Other Posts\nNIT Trichy Recruitment 2025 - Walk-in-Interview for Junior Research Fellow and Project Associate Post\nICSIL Recruitment 2025 - Apply Online for 02 Project Associate Posts\nRRB Recruitment 2025 - Apply Online for 368 Section Controller Posts\nDHS Cuddalore Recruitment 2025 - Apply Offline 06 Consultant and Other Posts\nIB Recruitment 2025 - Apply Online for 394 Junior Intelligent Officer Grade-II Posts\nNTPC Recruitment 2025 - Apply Online for 20 Physician Posts\nWCD Odisha Recruitment 2025 - Apply Online for 91 Anganwadi Worker & Helper Posts\nJobs By Qualification\n10th8thAeronautical EngineeringAgricultural EngineeringANMAny DegreeArchitectural EngineeringAutomobile EngineeringB.E/ B.TechB.EdB.PharmB.ScB.sc NursingB.V.ScBAMSBDSBHMSBiotechnologyBPTBUMSCA/ ICWAIChemical EngineeringCivil EngineeringComputer Science EngineeringD. PharmaDiplomaDMLTDNBElectrical and InstrumentationElectrical EngineeringElectronics and Communication EngineeringEngineeringGATEGNMHotel ManagementInformation TechnologyIntermediate (10+2)ITILLBM.AM.E / M.TechM.PharmM.Phil / Ph.DM.ScM.sc NursingM.V.ScMBAMBBSMCAMDSMechanical EngineeringMedicalMining EngineeringMS/ MDPetroleum EngineeringPGDMPharm DPharmacyPost GraduationSports QuotaStaff Nurse\n   All Government Jobs\nAllGovernmentJobs.in, founded in 2015, is a government job portal built with a robust search tool. We offer a wide range of Government Jobs, recruitment opportunities across India for free to help the job seekers. We proudly hold the position as the No.1 Job Portal across India, our company was accelerated through India’s largest Incubation centre T-Hub, Telangana, India.\nCompany\n Register\n Login\n About Us\n Contact Us\n Careers\n Terms & Conditions\n Privacy Policy\n Sitemap\n Subscribe\nPopular Pages\n Government Jobs\n Employment News\n Free Job Alert\n State Government Jobs\n Central Government Jobs\n Govt Jobs by Education\n Govt Jobs by Organisation\n Govt Jobs by Roles\n Govt Jobs by Location\nPopular Pages\n Previous Papers\n Results\n Admit Card\n Answer Keys\n Syllabus\nFollow us On\n    \n \nMade with Love in India © 2025 AllGovernmentjobs. All rights reserved",
      "paragraphs": [
        "The Mishra Dhatu Nigam Limited (MIDHANI) has announced the notification to fill the vacancies of 50 Assistant Posts. Eligible applicants can use this opportunity to apply for these posts before the application deadline. Candidates who have completed their Diploma in Electrical, Mechanical Engineering, 10th, and ITI may apply for the MIDHANI Recruitment 2025. The interested applicants can attend the Direct interview. Details provided include the education details, Age criteria, Selection procedure, Processing fee, salary, and Application process for these posts before the deadline. The application dates have already begun.",
        "If you are more interested in Government Jobs, candidates can also apply for jobs in Telangana.",
        "MIDHANI Recruitment 2025 Age Limit:",
        "MIDHANI Recruitment 2025 Selection Process:",
        "MIDHANI Recruitment 2025 Application Fee:",
        "MIDHANI Recruitment 2025 Pay Scale:",
        "MIDHANI Corporate Office Auditorium, Kanchanbagh, Hyderabad – 500 058.",
        "Important Dates:",
        "Posted on - 22 Aug 2025",
        "Posted on - 22 Aug 2025",
        "Posted on - 22 Aug 2025",
        "Posted on - 22 Aug 2025",
        "Posted on - 22 Aug 2025",
        "Posted on - 22 Aug 2025",
        "Posted on - 22 Aug 2025",
        "Posted on - 22 Aug 2025",
        "Posted on - 22 Aug 2025",
        "Posted on - 22 Aug 2025",
        "Subscribe to Get Latest Updates"
      ],
      "tables": [
        {
          "index": 0,
          "html": "<table class=\"table table-striped table-bordered\" style=\"border-collapse: collapse; width: 100%;\" border=\"1\"><tbody><tr style=\"height: 18px;\"><td style=\"width: 33.3333%; height: 18px; text-align: center;\"><strong>Name of the Posts</strong></td><td style=\"width: 33.3333%; height: 18px; text-align: center;\"><strong>Vacancies</strong></td><td style=\"width: 33.3333%; height: 18px; text-align: center;\"><strong>Education</strong></td></tr><tr style=\"height: 36px;\"><td style=\"width: 33.3333%; height: 36px; text-align: center;\">Assistant Level-4 &amp; Level-2</td><td style=\"width: 33.3333%; height: 36px; text-align: center;\">50</td><td style=\"width: 33.3333%; height: 36px; text-align: center;\">Diploma in Electrical, <a href=\"https://allgovernmentjobs.in/mechanical-engineering-jobs\"><span style=\"color: #0000ff;\"><strong>Mechanical Engineering</strong></span></a>, <a href=\"https://allgovernmentjobs.in/10th-pass-govt-jobs\"><span style=\"color: #0000ff;\"><strong>10th pass</strong></span></a>, ITI</td></tr></tbody></table>",
          "rows": [
            [
              {
                "text": "Name of the Posts",
                "html": "<strong>Name of the Posts</strong>",
                "isHeader": false,
                "colspan": null,
                "rowspan": null,
                "links": []
              },
              {
                "text": "Vacancies",
                "html": "<strong>Vacancies</strong>",
                "isHeader": false,
                "colspan": null,
                "rowspan": null,
                "links": []
              },
              {
                "text": "Education",
                "html": "<strong>Education</strong>",
                "isHeader": false,
                "colspan": null,
                "rowspan": null,
                "links": []
              }
            ],
            [
              {
                "text": "Assistant Level-4 & Level-2",
                "html": "Assistant Level-4 &amp; Level-2",
                "isHeader": false,
                "colspan": null,
                "rowspan": null,
                "links": []
              },
              {
                "text": "50",
                "html": "50",
                "isHeader": false,
                "colspan": null,
                "rowspan": null,
                "links": []
              },
              {
                "text": "Diploma in Electrical, Mechanical Engineering, 10th pass, ITI",
                "html": "Diploma in Electrical, <a href=\"https://allgovernmentjobs.in/mechanical-engineering-jobs\"><span style=\"color: #0000ff;\"><strong>Mechanical Engineering</strong></span></a>, <a href=\"https://allgovernmentjobs.in/10th-pass-govt-jobs\"><span style=\"color: #0000ff;\"><strong>10th pass</strong></span></a>, ITI",
                "isHeader": false,
                "colspan": null,
                "rowspan": null,
                "links": [
                  {
                    "text": "Mechanical Engineering",
                    "href": "https://allgovernmentjobs.in/mechanical-engineering-jobs"
                  },
                  {
                    "text": "10th pass",
                    "href": "https://allgovernmentjobs.in/10th-pass-govt-jobs"
                  }
                ]
              }
            ]
          ]
        },
        {
          "index": 1,
          "html": "<table class=\"table table-striped table-bordered\" style=\"border-collapse: collapse; width: 100%;\" border=\"1\"><tbody><tr><td style=\"width: 50%; text-align: center;\">Starting date</td><td style=\"width: 50%; text-align: center;\">21-08-2025</td></tr><tr><td style=\"width: 50%; text-align: center;\">Closing date</td><td style=\"width: 50%; text-align: center;\">17-09-2025</td></tr></tbody></table>",
          "rows": [
            [
              {
                "text": "Starting date",
                "html": "Starting date",
                "isHeader": false,
                "colspan": null,
                "rowspan": null,
                "links": []
              },
              {
                "text": "21-08-2025",
                "html": "21-08-2025",
                "isHeader": false,
                "colspan": null,
                "rowspan": null,
                "links": []
              }
            ],
            [
              {
                "text": "Closing date",
                "html": "Closing date",
                "isHeader": false,
                "colspan": null,
                "rowspan": null,
                "links": []
              },
              {
                "text": "17-09-2025",
                "html": "17-09-2025",
                "isHeader": false,
                "colspan": null,
                "rowspan": null,
                "links": []
              }
            ]
          ]
        },
        {
          "index": 2,
          "html": "<table class=\"table table-bordered\"><tbody><tr><td><b>Official Notification</b></td><td class=\"text-center\"><a target=\"_blank\" href=\"https://files.allgovernmentjobs.in/public/2025/08/1755836585d290652f8d5fae8ea0982d25b8c3210334922dfe.pdf\" rel=\"nofollow\"><b class=\"text-primary\">Click Here</b></a></td></tr><tr><td><b>Join Whatsapp Group</b></td><td class=\"text-center\"><a target=\"_blank\" href=\"https://whatsapp.com/channel/0029VaBuWFt5fM5WmENN541K\" data-action=\"share/whatsapp/share\"><b class=\"text-primary\">Join Now</b></a></td></tr><tr><td><b>Join on Telegram</b></td><td class=\"text-center\"><a target=\"_blank\" href=\"https://t.me/govtjobs9\"><b class=\"text-primary\">Join Now</b></a></td></tr></tbody></table>",
          "rows": [
            [
              {
                "text": "Official Notification",
                "html": "<b>Official Notification</b>",
                "isHeader": false,
                "colspan": null,
                "rowspan": null,
                "links": []
              },
              {
                "text": "Click Here",
                "html": "<a target=\"_blank\" href=\"https://files.allgovernmentjobs.in/public/2025/08/1755836585d290652f8d5fae8ea0982d25b8c3210334922dfe.pdf\" rel=\"nofollow\"><b class=\"text-primary\">Click Here</b></a>",
                "isHeader": false,
                "colspan": null,
                "rowspan": null,
                "links": [
                  {
                    "text": "Click Here",
                    "href": "https://files.allgovernmentjobs.in/public/2025/08/1755836585d290652f8d5fae8ea0982d25b8c3210334922dfe.pdf"
                  }
                ]
              }
            ],
            [
              {
                "text": "Join Whatsapp Group",
                "html": "<b>Join Whatsapp Group</b>",
                "isHeader": false,
                "colspan": null,
                "rowspan": null,
                "links": []
              },
              {
                "text": "Join Now",
                "html": "<a target=\"_blank\" href=\"https://whatsapp.com/channel/0029VaBuWFt5fM5WmENN541K\" data-action=\"share/whatsapp/share\"><b class=\"text-primary\">Join Now</b></a>",
                "isHeader": false,
                "colspan": null,
                "rowspan": null,
                "links": [
                  {
                    "text": "Join Now",
                    "href": "https://whatsapp.com/channel/0029VaBuWFt5fM5WmENN541K"
                  }
                ]
              }
            ],
            [
              {
                "text": "Join on Telegram",
                "html": "<b>Join on Telegram</b>",
                "isHeader": false,
                "colspan": null,
                "rowspan": null,
                "links": []
              },
              {
                "text": "Join Now",
                "html": "<a target=\"_blank\" href=\"https://t.me/govtjobs9\"><b class=\"text-primary\">Join Now</b></a>",
                "isHeader": false,
                "colspan": null,
                "rowspan": null,
                "links": [
                  {
                    "text": "Join Now",
                    "href": "https://t.me/govtjobs9"
                  }
                ]
              }
            ]
          ]
        },
        {
          "index": 3,
          "html": "<table class=\"table table-striped table-bordered\"><thead><tr style=\"background-color: #2c5782; color: #fff;\" class=\"text-center\"><th>Board</th><th>Post Name</th><th>Vacancies</th><th>Details</th></tr></thead><tbody><tr><td class=\"align-middle\"><a class=\"text-primary\" href=\"indian-bank-recruitment\">Indian Bank</a></td><td>Attender Jobs<p class=\"text-muted mb-0\">Posted on - 22 Aug 2025</p></td><td><div>01</div></td><td style=\"min-width: 141px;\" class=\"align-middle\"><a class=\"btn btn-sm m-0 btn-outline-primary waves-effect\" href=\"https://allgovernmentjobs.in/indian-bank-recruitment-2025-apply-offline-for-attender-post/34255\">View / Apply</a></td></tr><tr><td class=\"align-middle\"><a class=\"text-primary\" href=\"rrb-recruitment\">RRB</a></td><td>Project Engineer Jobs<p class=\"text-muted mb-0\">Posted on - 22 Aug 2025</p></td><td><div>04</div></td><td style=\"min-width: 141px;\" class=\"align-middle\"><a class=\"btn btn-sm m-0 btn-outline-primary waves-effect\" href=\"https://allgovernmentjobs.in/mrvc-recruitment-2025-apply-offline-for-04-project-engineer-posts/34254\">View / Apply</a></td></tr><tr><td class=\"align-middle\"><a class=\"text-primary\" href=\"nhm-recruitment\">NHM</a></td><td>Therapeutic , Multi Purpose Hospital Worker, Consultant, attender Jobs<p class=\"text-muted mb-0\">Posted on - 22 Aug 2025</p></td><td><div>09</div></td><td style=\"min-width: 141px;\" class=\"align-middle\"><a class=\"btn btn-sm m-0 btn-outline-primary waves-effect\" href=\"https://allgovernmentjobs.in/dhs-cuddalore-recruitment-2025-apply-offline-06-consultant-and-other-posts/34249\">View / Apply</a></td></tr><tr><td class=\"align-middle\"><a class=\"text-primary\" href=\"intelligence-bureau-recruitment\">Intelligence Bureau</a></td><td>Junior Intelligence Officer Grade-II Jobs<p class=\"text-muted mb-0\">Posted on - 22 Aug 2025</p></td><td><div>394</div></td><td style=\"min-width: 141px;\" class=\"align-middle\"><a class=\"btn btn-sm m-0 btn-outline-primary waves-effect\" href=\"https://allgovernmentjobs.in/ib-recruitment-2025-apply-online-for-394-junior-intelligent-officer-grade-ii-posts/34248\">View / Apply</a></td></tr><tr><td class=\"align-middle\"><a class=\"text-primary\" href=\"ucil-recruitment\">UCIL</a></td><td>Management Trainee, Diploma Trainee, Graduate Operational Trainee Jobs<p class=\"text-muted mb-0\">Posted on - 22 Aug 2025</p></td><td><div>99</div></td><td style=\"min-width: 141px;\" class=\"align-middle\"><a class=\"btn btn-sm m-0 btn-outline-primary waves-effect\" href=\"https://allgovernmentjobs.in/ucil-recruitment-2025-apply-online-for-99-management-diploma-trainee-posts/34242\">View / Apply</a></td></tr><tr><td class=\"align-middle\"><a class=\"text-primary\" href=\"wcr-recruitment\">WCR </a></td><td>Apprentice Jobs<p class=\"text-muted mb-0\">Posted on - 22 Aug 2025</p></td><td><div>2865</div></td><td style=\"min-width: 141px;\" class=\"align-middle\"><a class=\"btn btn-sm m-0 btn-outline-primary waves-effect\" href=\"https://allgovernmentjobs.in/wcr-recruitment-2025-apply-online-for-2865-apprentices-posts/34239\">View / Apply</a></td></tr><tr><td class=\"align-middle\"><a class=\"text-primary\" href=\"cci-recruitment\">CCI</a></td><td>Security Guard Jobs<p class=\"text-muted mb-0\">Posted on - 22 Aug 2025</p></td><td><div>01</div></td><td style=\"min-width: 141px;\" class=\"align-middle\"><a class=\"btn btn-sm m-0 btn-outline-primary waves-effect\" href=\"https://allgovernmentjobs.in/ccil-recruitment-2025-walk-n-interview-for-security-guard-post/34237\">View / Apply</a></td></tr><tr><td class=\"align-middle\"><a class=\"text-primary\" href=\"isro-recruitment\">ISRO</a></td><td>Graduate Apprentice Jobs<p class=\"text-muted mb-0\">Posted on - 22 Aug 2025</p></td><td><div>96</div></td><td style=\"min-width: 141px;\" class=\"align-middle\"><a class=\"btn btn-sm m-0 btn-outline-primary waves-effect\" href=\"https://allgovernmentjobs.in/isro-nrsc-recruitment-2025-apply-online-for-96-apprentice-posts/34233\">View / Apply</a></td></tr><tr><td class=\"align-middle\"><a class=\"text-primary\" href=\"nhm-recruitment\">NHM</a></td><td>Nurse, Pharmacist, Lab Technician, Support Staff, Counsellor Jobs<p class=\"text-muted mb-0\">Posted on - 22 Aug 2025</p></td><td><div>33</div></td><td style=\"min-width: 141px;\" class=\"align-middle\"><a class=\"btn btn-sm m-0 btn-outline-primary waves-effect\" href=\"https://allgovernmentjobs.in/dhs-kanniyakumari-recruitment-2025-apply-offline-for-33-nurse-pharmacist-and-other-posts/34081\">View / Apply</a></td></tr><tr><td class=\"align-middle\"><a class=\"text-primary\" href=\"svnit-recruitment\">SVNIT</a></td><td>Junior Research Fellow Jobs<p class=\"text-muted mb-0\">Posted on - 22 Aug 2025</p></td><td><div>01</div></td><td style=\"min-width: 141px;\" class=\"align-middle\"><a class=\"btn btn-sm m-0 btn-outline-primary waves-effect\" href=\"https://allgovernmentjobs.in/svnit-recruitment-2025-apply-for-junior-research-fellow-post/34231\">View / Apply</a></td></tr></tbody></table>",
          "rows": [
            [
              {
                "text": "Board",
                "html": "Board",
                "isHeader": true,
                "colspan": null,
                "rowspan": null,
                "links": []
              },
              {
                "text": "Post Name",
                "html": "Post Name",
                "isHeader": true,
                "colspan": null,
                "rowspan": null,
                "links": []
              },
              {
                "text": "Vacancies",
                "html": "Vacancies",
                "isHeader": true,
                "colspan": null,
                "rowspan": null,
                "links": []
              },
              {
                "text": "Details",
                "html": "Details",
                "isHeader": true,
                "colspan": null,
                "rowspan": null,
                "links": []
              }
            ],
            [
              {
                "text": "Indian Bank",
                "html": "<a class=\"text-primary\" href=\"indian-bank-recruitment\">Indian Bank</a>",
                "isHeader": false,
                "colspan": null,
                "rowspan": null,
                "links": [
                  {
                    "text": "Indian Bank",
                    "href": "https://allgovernmentjobs.in/indian-bank-recruitment"
                  }
                ]
              },
              {
                "text": "Attender JobsPosted on - 22 Aug 2025",
                "html": "Attender Jobs<p class=\"text-muted mb-0\">Posted on - 22 Aug 2025</p>",
                "isHeader": false,
                "colspan": null,
                "rowspan": null,
                "links": []
              },
              {
                "text": "01",
                "html": "<div>01</div>",
                "isHeader": false,
                "colspan": null,
                "rowspan": null,
                "links": []
              },
              {
                "text": "View / Apply",
                "html": "<a class=\"btn btn-sm m-0 btn-outline-primary waves-effect\" href=\"https://allgovernmentjobs.in/indian-bank-recruitment-2025-apply-offline-for-attender-post/34255\">View / Apply</a>",
                "isHeader": false,
                "colspan": null,
                "rowspan": null,
                "links": [
                  {
                    "text": "View / Apply",
                    "href": "https://allgovernmentjobs.in/indian-bank-recruitment-2025-apply-offline-for-attender-post/34255"
                  }
                ]
              }
            ],
            [
              {
                "text": "RRB",
                "html": "<a class=\"text-primary\" href=\"rrb-recruitment\">RRB</a>",
                "isHeader": false,
                "colspan": null,
                "rowspan": null,
                "links": [
                  {
                    "text": "RRB",
                    "href": "https://allgovernmentjobs.in/rrb-recruitment"
                  }
                ]
              },
              {
                "text": "Project Engineer JobsPosted on - 22 Aug 2025",
                "html": "Project Engineer Jobs<p class=\"text-muted mb-0\">Posted on - 22 Aug 2025</p>",
                "isHeader": false,
                "colspan": null,
                "rowspan": null,
                "links": []
              },
              {
                "text": "04",
                "html": "<div>04</div>",
                "isHeader": false,
                "colspan": null,
                "rowspan": null,
                "links": []
              },
              {
                "text": "View / Apply",
                "html": "<a class=\"btn btn-sm m-0 btn-outline-primary waves-effect\" href=\"https://allgovernmentjobs.in/mrvc-recruitment-2025-apply-offline-for-04-project-engineer-posts/34254\">View / Apply</a>",
                "isHeader": false,
                "colspan": null,
                "rowspan": null,
                "links": [
                  {
                    "text": "View / Apply",
                    "href": "https://allgovernmentjobs.in/mrvc-recruitment-2025-apply-offline-for-04-project-engineer-posts/34254"
                  }
                ]
              }
            ],
            [
              {
                "text": "NHM",
                "html": "<a class=\"text-primary\" href=\"nhm-recruitment\">NHM</a>",
                "isHeader": false,
                "colspan": null,
                "rowspan": null,
                "links": [
                  {
                    "text": "NHM",
                    "href": "https://allgovernmentjobs.in/nhm-recruitment"
                  }
                ]
              },
              {
                "text": "Therapeutic , Multi Purpose Hospital Worker, Consultant, attender JobsPosted on - 22 Aug 2025",
                "html": "Therapeutic , Multi Purpose Hospital Worker, Consultant, attender Jobs<p class=\"text-muted mb-0\">Posted on - 22 Aug 2025</p>",
                "isHeader": false,
                "colspan": null,
                "rowspan": null,
                "links": []
              },
              {
                "text": "09",
                "html": "<div>09</div>",
                "isHeader": false,
                "colspan": null,
                "rowspan": null,
                "links": []
              },
              {
                "text": "View / Apply",
                "html": "<a class=\"btn btn-sm m-0 btn-outline-primary waves-effect\" href=\"https://allgovernmentjobs.in/dhs-cuddalore-recruitment-2025-apply-offline-06-consultant-and-other-posts/34249\">View / Apply</a>",
                "isHeader": false,
                "colspan": null,
                "rowspan": null,
                "links": [
                  {
                    "text": "View / Apply",
                    "href": "https://allgovernmentjobs.in/dhs-cuddalore-recruitment-2025-apply-offline-06-consultant-and-other-posts/34249"
                  }
                ]
              }
            ],
            [
              {
                "text": "Intelligence Bureau",
                "html": "<a class=\"text-primary\" href=\"intelligence-bureau-recruitment\">Intelligence Bureau</a>",
                "isHeader": false,
                "colspan": null,
                "rowspan": null,
                "links": [
                  {
                    "text": "Intelligence Bureau",
                    "href": "https://allgovernmentjobs.in/intelligence-bureau-recruitment"
                  }
                ]
              },
              {
                "text": "Junior Intelligence Officer Grade-II JobsPosted on - 22 Aug 2025",
                "html": "Junior Intelligence Officer Grade-II Jobs<p class=\"text-muted mb-0\">Posted on - 22 Aug 2025</p>",
                "isHeader": false,
                "colspan": null,
                "rowspan": null,
                "links": []
              },
              {
                "text": "394",
                "html": "<div>394</div>",
                "isHeader": false,
                "colspan": null,
                "rowspan": null,
                "links": []
              },
              {
                "text": "View / Apply",
                "html": "<a class=\"btn btn-sm m-0 btn-outline-primary waves-effect\" href=\"https://allgovernmentjobs.in/ib-recruitment-2025-apply-online-for-394-junior-intelligent-officer-grade-ii-posts/34248\">View / Apply</a>",
                "isHeader": false,
                "colspan": null,
                "rowspan": null,
                "links": [
                  {
                    "text": "View / Apply",
                    "href": "https://allgovernmentjobs.in/ib-recruitment-2025-apply-online-for-394-junior-intelligent-officer-grade-ii-posts/34248"
                  }
                ]
              }
            ],
            [
              {
                "text": "UCIL",
                "html": "<a class=\"text-primary\" href=\"ucil-recruitment\">UCIL</a>",
                "isHeader": false,
                "colspan": null,
                "rowspan": null,
                "links": [
                  {
                    "text": "UCIL",
                    "href": "https://allgovernmentjobs.in/ucil-recruitment"
                  }
                ]
              },
              {
                "text": "Management Trainee, Diploma Trainee, Graduate Operational Trainee JobsPosted on - 22 Aug 2025",
                "html": "Management Trainee, Diploma Trainee, Graduate Operational Trainee Jobs<p class=\"text-muted mb-0\">Posted on - 22 Aug 2025</p>",
                "isHeader": false,
                "colspan": null,
                "rowspan": null,
                "links": []
              },
              {
                "text": "99",
                "html": "<div>99</div>",
                "isHeader": false,
                "colspan": null,
                "rowspan": null,
                "links": []
              },
              {
                "text": "View / Apply",
                "html": "<a class=\"btn btn-sm m-0 btn-outline-primary waves-effect\" href=\"https://allgovernmentjobs.in/ucil-recruitment-2025-apply-online-for-99-management-diploma-trainee-posts/34242\">View / Apply</a>",
                "isHeader": false,
                "colspan": null,
                "rowspan": null,
                "links": [
                  {
                    "text": "View / Apply",
                    "href": "https://allgovernmentjobs.in/ucil-recruitment-2025-apply-online-for-99-management-diploma-trainee-posts/34242"
                  }
                ]
              }
            ],
            [
              {
                "text": "WCR",
                "html": "<a class=\"text-primary\" href=\"wcr-recruitment\">WCR </a>",
                "isHeader": false,
                "colspan": null,
                "rowspan": null,
                "links": [
                  {
                    "text": "WCR",
                    "href": "https://allgovernmentjobs.in/wcr-recruitment"
                  }
                ]
              },
              {
                "text": "Apprentice JobsPosted on - 22 Aug 2025",
                "html": "Apprentice Jobs<p class=\"text-muted mb-0\">Posted on - 22 Aug 2025</p>",
                "isHeader": false,
                "colspan": null,
                "rowspan": null,
                "links": []
              },
              {
                "text": "2865",
                "html": "<div>2865</div>",
                "isHeader": false,
                "colspan": null,
                "rowspan": null,
                "links": []
              },
              {
                "text": "View / Apply",
                "html": "<a class=\"btn btn-sm m-0 btn-outline-primary waves-effect\" href=\"https://allgovernmentjobs.in/wcr-recruitment-2025-apply-online-for-2865-apprentices-posts/34239\">View / Apply</a>",
                "isHeader": false,
                "colspan": null,
                "rowspan": null,
                "links": [
                  {
                    "text": "View / Apply",
                    "href": "https://allgovernmentjobs.in/wcr-recruitment-2025-apply-online-for-2865-apprentices-posts/34239"
                  }
                ]
              }
            ],
            [
              {
                "text": "CCI",
                "html": "<a class=\"text-primary\" href=\"cci-recruitment\">CCI</a>",
                "isHeader": false,
                "colspan": null,
                "rowspan": null,
                "links": [
                  {
                    "text": "CCI",
                    "href": "https://allgovernmentjobs.in/cci-recruitment"
                  }
                ]
              },
              {
                "text": "Security Guard JobsPosted on - 22 Aug 2025",
                "html": "Security Guard Jobs<p class=\"text-muted mb-0\">Posted on - 22 Aug 2025</p>",
                "isHeader": false,
                "colspan": null,
                "rowspan": null,
                "links": []
              },
              {
                "text": "01",
                "html": "<div>01</div>",
                "isHeader": false,
                "colspan": null,
                "rowspan": null,
                "links": []
              },
              {
                "text": "View / Apply",
                "html": "<a class=\"btn btn-sm m-0 btn-outline-primary waves-effect\" href=\"https://allgovernmentjobs.in/ccil-recruitment-2025-walk-n-interview-for-security-guard-post/34237\">View / Apply</a>",
                "isHeader": false,
                "colspan": null,
                "rowspan": null,
                "links": [
                  {
                    "text": "View / Apply",
                    "href": "https://allgovernmentjobs.in/ccil-recruitment-2025-walk-n-interview-for-security-guard-post/34237"
                  }
                ]
              }
            ],
            [
              {
                "text": "ISRO",
                "html": "<a class=\"text-primary\" href=\"isro-recruitment\">ISRO</a>",
                "isHeader": false,
                "colspan": null,
                "rowspan": null,
                "links": [
                  {
                    "text": "ISRO",
                    "href": "https://allgovernmentjobs.in/isro-recruitment"
                  }
                ]
              },
              {
                "text": "Graduate Apprentice JobsPosted on - 22 Aug 2025",
                "html": "Graduate Apprentice Jobs<p class=\"text-muted mb-0\">Posted on - 22 Aug 2025</p>",
                "isHeader": false,
                "colspan": null,
                "rowspan": null,
                "links": []
              },
              {
                "text": "96",
                "html": "<div>96</div>",
                "isHeader": false,
                "colspan": null,
                "rowspan": null,
                "links": []
              },
              {
                "text": "View / Apply",
                "html": "<a class=\"btn btn-sm m-0 btn-outline-primary waves-effect\" href=\"https://allgovernmentjobs.in/isro-nrsc-recruitment-2025-apply-online-for-96-apprentice-posts/34233\">View / Apply</a>",
                "isHeader": false,
                "colspan": null,
                "rowspan": null,
                "links": [
                  {
                    "text": "View / Apply",
                    "href": "https://allgovernmentjobs.in/isro-nrsc-recruitment-2025-apply-online-for-96-apprentice-posts/34233"
                  }
                ]
              }
            ],
            [
              {
                "text": "NHM",
                "html": "<a class=\"text-primary\" href=\"nhm-recruitment\">NHM</a>",
                "isHeader": false,
                "colspan": null,
                "rowspan": null,
                "links": [
                  {
                    "text": "NHM",
                    "href": "https://allgovernmentjobs.in/nhm-recruitment"
                  }
                ]
              },
              {
                "text": "Nurse, Pharmacist, Lab Technician, Support Staff, Counsellor JobsPosted on - 22 Aug 2025",
                "html": "Nurse, Pharmacist, Lab Technician, Support Staff, Counsellor Jobs<p class=\"text-muted mb-0\">Posted on - 22 Aug 2025</p>",
                "isHeader": false,
                "colspan": null,
                "rowspan": null,
                "links": []
              },
              {
                "text": "33",
                "html": "<div>33</div>",
                "isHeader": false,
                "colspan": null,
                "rowspan": null,
                "links": []
              },
              {
                "text": "View / Apply",
                "html": "<a class=\"btn btn-sm m-0 btn-outline-primary waves-effect\" href=\"https://allgovernmentjobs.in/dhs-kanniyakumari-recruitment-2025-apply-offline-for-33-nurse-pharmacist-and-other-posts/34081\">View / Apply</a>",
                "isHeader": false,
                "colspan": null,
                "rowspan": null,
                "links": [
                  {
                    "text": "View / Apply",
                    "href": "https://allgovernmentjobs.in/dhs-kanniyakumari-recruitment-2025-apply-offline-for-33-nurse-pharmacist-and-other-posts/34081"
                  }
                ]
              }
            ],
            [
              {
                "text": "SVNIT",
                "html": "<a class=\"text-primary\" href=\"svnit-recruitment\">SVNIT</a>",
                "isHeader": false,
                "colspan": null,
                "rowspan": null,
                "links": [
                  {
                    "text": "SVNIT",
                    "href": "https://allgovernmentjobs.in/svnit-recruitment"
                  }
                ]
              },
              {
                "text": "Junior Research Fellow JobsPosted on - 22 Aug 2025",
                "html": "Junior Research Fellow Jobs<p class=\"text-muted mb-0\">Posted on - 22 Aug 2025</p>",
                "isHeader": false,
                "colspan": null,
                "rowspan": null,
                "links": []
              },
              {
                "text": "01",
                "html": "<div>01</div>",
                "isHeader": false,
                "colspan": null,
                "rowspan": null,
                "links": []
              },
              {
                "text": "View / Apply",
                "html": "<a class=\"btn btn-sm m-0 btn-outline-primary waves-effect\" href=\"https://allgovernmentjobs.in/svnit-recruitment-2025-apply-for-junior-research-fellow-post/34231\">View / Apply</a>",
                "isHeader": false,
                "colspan": null,
                "rowspan": null,
                "links": [
                  {
                    "text": "View / Apply",
                    "href": "https://allgovernmentjobs.in/svnit-recruitment-2025-apply-for-junior-research-fellow-post/34231"
                  }
                ]
              }
            ]
          ]
        }
      ],
      "lists": [
        {
          "type": "UL",
          "items": [
            "Home",
            "Latest Govt Jobs",
            "Results",
            "Qualifications",
            "Organizations",
            "About Us",
            "Contact Us",
            "Register",
            "Login"
          ]
        },
        {
          "type": "UL",
          "items": [
            "The minimum age limit: 18 Years.",
            "The maximum age limit: 35 Years.",
            "Age relaxation is based on the Organisation's norms."
          ]
        },
        {
          "type": "UL",
          "items": [
            "The selection process is based on the interview."
          ]
        },
        {
          "type": "UL",
          "items": [
            "There is no application fee."
          ]
        },
        {
          "type": "UL",
          "items": [
            "The minimum salary: Rs. 29,800/- per month.",
            "The maximum salary: Rs. 32.640/- per month."
          ]
        },
        {
          "type": "UL",
          "items": [
            "Go to the official website.",
            "Visit the MIDHANI Recruitment 2025 notification.",
            "Read the instructions carefully and check the eligiblity criteria.",
            "If you are eligible.",
            "Gather all the required documents.",
            "Carry all the documents to the interview.",
            "Attend the interview at the mentioned address."
          ]
        },
        {
          "type": "UL",
          "items": [
            "Government Jobs",
            "Engineering Jobs",
            "Medical Jobs",
            "Any Degree Jobs",
            "Nursing Jobs",
            "Civil Engineering Jobs",
            "10th Pass Govt Job",
            "Pharmacist Vacancy"
          ]
        },
        {
          "type": "UL",
          "items": [
            "Indian Bank Recruitment 2025 - Apply Offline for Attender Post",
            "MRVC Recruitment 2025 - Apply Offline for 04 Project Engineer Posts",
            "IFGTB Recruitment 2025 - Apply Online for 13 Research Associate and Other Posts",
            "NIT Trichy Recruitment 2025 - Walk-in-Interview for Junior Research Fellow and Project Associate Post",
            "ICSIL Recruitment 2025 - Apply Online for 02 Project Associate Posts",
            "RRB Recruitment 2025 - Apply Online for 368 Section Controller Posts",
            "DHS Cuddalore Recruitment 2025 - Apply Offline 06 Consultant and Other Posts",
            "IB Recruitment 2025 - Apply Online for 394 Junior Intelligent Officer Grade-II Posts",
            "NTPC Recruitment 2025 - Apply Online for 20 Physician Posts",
            "WCD Odisha Recruitment 2025 - Apply Online for 91 Anganwadi Worker & Helper Posts"
          ]
        },
        {
          "type": "UL",
          "items": [
            "Register",
            "Login",
            "About Us",
            "Contact Us",
            "Careers",
            "Terms & Conditions",
            "Privacy Policy",
            "Sitemap",
            "Subscribe"
          ]
        },
        {
          "type": "UL",
          "items": [
            "Government Jobs",
            "Employment News",
            "Free Job Alert",
            "State Government Jobs",
            "Central Government Jobs",
            "Govt Jobs by Education",
            "Govt Jobs by Organisation",
            "Govt Jobs by Roles",
            "Govt Jobs by Location"
          ]
        },
        {
          "type": "UL",
          "items": [
            "Previous Papers",
            "Results",
            "Admit Card",
            "Answer Keys",
            "Syllabus"
          ]
        }
      ],
      "links": [
        {
          "text": "Join on Telegram",
          "href": "https://t.me/govtjobs9"
        },
        {
          "text": "All Government Jobs",
          "href": "https://allgovernmentjobs.in/"
        },
        {
          "text": "Home",
          "href": "https://allgovernmentjobs.in/"
        },
        {
          "text": "Latest Govt Jobs",
          "href": "https://allgovernmentjobs.in/latest-government-jobs"
        },
        {
          "text": "Results",
          "href": "https://allgovernmentjobs.in/results"
        },
        {
          "text": "Qualifications",
          "href": "https://allgovernmentjobs.in/jobs-by-qualification"
        },
        {
          "text": "Organizations",
          "href": "https://allgovernmentjobs.in/jobs-by-organization"
        },
        {
          "text": "About Us",
          "href": "https://allgovernmentjobs.in/about-us"
        },
        {
          "text": "Contact Us",
          "href": "https://allgovernmentjobs.in/contact-us"
        },
        {
          "text": "Register",
          "href": "https://allgovernmentjobs.in/register"
        },
        {
          "text": "Login",
          "href": "https://allgovernmentjobs.in/login"
        },
        {
          "text": "Home",
          "href": "https://allgovernmentjobs.in/"
        },
        {
          "text": "Midhani Recruitment",
          "href": "https://allgovernmentjobs.in/midhani-recruitment"
        },
        {
          "text": "Harshitha",
          "href": "https://allgovernmentjobs.in/author/harshitha"
        },
        {
          "text": "Mishtra Dhatu Nigam Limited",
          "href": "https://allgovernmentjobs.in/midhani-recruitment"
        },
        {
          "text": "Telangana",
          "href": "https://allgovernmentjobs.in/govt-jobs-in-telangana"
        },
        {
          "text": "MIDHANI Recruitment 2025",
          "href": "https://allgovernmentjobs.in/midhani-recruitment"
        },
        {
          "text": "Government Jobs",
          "href": "https://allgovernmentjobs.in/"
        },
        {
          "text": "Telangana.",
          "href": "https://allgovernmentjobs.in/govt-jobs-in-telangana"
        },
        {
          "text": "Mechanical Engineering",
          "href": "https://allgovernmentjobs.in/mechanical-engineering-jobs"
        },
        {
          "text": "10th pass",
          "href": "https://allgovernmentjobs.in/10th-pass-govt-jobs"
        },
        {
          "text": "Click Here",
          "href": "https://files.allgovernmentjobs.in/public/2025/08/1755836585d290652f8d5fae8ea0982d25b8c3210334922dfe.pdf"
        },
        {
          "text": "Join Now",
          "href": "https://whatsapp.com/channel/0029VaBuWFt5fM5WmENN541K"
        },
        {
          "text": "Join Now",
          "href": "https://t.me/govtjobs9"
        },
        {
          "text": "Join Whatsapp Group",
          "href": "https://whatsapp.com/channel/0029VaBuWFt5fM5WmENN541K"
        },
        {
          "text": "Join on Telegram",
          "href": "https://t.me/govtjobs9"
        },
        {
          "text": "Indian Bank",
          "href": "https://allgovernmentjobs.in/indian-bank-recruitment"
        },
        {
          "text": "View / Apply",
          "href": "https://allgovernmentjobs.in/indian-bank-recruitment-2025-apply-offline-for-attender-post/34255"
        },
        {
          "text": "RRB",
          "href": "https://allgovernmentjobs.in/rrb-recruitment"
        },
        {
          "text": "View / Apply",
          "href": "https://allgovernmentjobs.in/mrvc-recruitment-2025-apply-offline-for-04-project-engineer-posts/34254"
        },
        {
          "text": "NHM",
          "href": "https://allgovernmentjobs.in/nhm-recruitment"
        },
        {
          "text": "View / Apply",
          "href": "https://allgovernmentjobs.in/dhs-cuddalore-recruitment-2025-apply-offline-06-consultant-and-other-posts/34249"
        },
        {
          "text": "Intelligence Bureau",
          "href": "https://allgovernmentjobs.in/intelligence-bureau-recruitment"
        },
        {
          "text": "View / Apply",
          "href": "https://allgovernmentjobs.in/ib-recruitment-2025-apply-online-for-394-junior-intelligent-officer-grade-ii-posts/34248"
        },
        {
          "text": "UCIL",
          "href": "https://allgovernmentjobs.in/ucil-recruitment"
        },
        {
          "text": "View / Apply",
          "href": "https://allgovernmentjobs.in/ucil-recruitment-2025-apply-online-for-99-management-diploma-trainee-posts/34242"
        },
        {
          "text": "WCR",
          "href": "https://allgovernmentjobs.in/wcr-recruitment"
        },
        {
          "text": "View / Apply",
          "href": "https://allgovernmentjobs.in/wcr-recruitment-2025-apply-online-for-2865-apprentices-posts/34239"
        },
        {
          "text": "CCI",
          "href": "https://allgovernmentjobs.in/cci-recruitment"
        },
        {
          "text": "View / Apply",
          "href": "https://allgovernmentjobs.in/ccil-recruitment-2025-walk-n-interview-for-security-guard-post/34237"
        },
        {
          "text": "ISRO",
          "href": "https://allgovernmentjobs.in/isro-recruitment"
        },
        {
          "text": "View / Apply",
          "href": "https://allgovernmentjobs.in/isro-nrsc-recruitment-2025-apply-online-for-96-apprentice-posts/34233"
        },
        {
          "text": "NHM",
          "href": "https://allgovernmentjobs.in/nhm-recruitment"
        },
        {
          "text": "View / Apply",
          "href": "https://allgovernmentjobs.in/dhs-kanniyakumari-recruitment-2025-apply-offline-for-33-nurse-pharmacist-and-other-posts/34081"
        },
        {
          "text": "SVNIT",
          "href": "https://allgovernmentjobs.in/svnit-recruitment"
        },
        {
          "text": "View / Apply",
          "href": "https://allgovernmentjobs.in/svnit-recruitment-2025-apply-for-junior-research-fellow-post/34231"
        },
        {
          "text": "Subscribe",
          "href": "https://allgovernmentjobs.in/register"
        },
        {
          "text": "Join Whatsapp Group",
          "href": "https://whatsapp.com/channel/0029VaBuWFt5fM5WmENN541K"
        },
        {
          "text": "Join on Telegram",
          "href": "https://t.me/govtjobs9"
        },
        {
          "text": "Like us on Facebook",
          "href": "https://www.facebook.com/allgovernmentjobsin/"
        },
        {
          "text": "Follow on Twitter",
          "href": "https://twitter.com/allgovtjobsin"
        },
        {
          "text": "Subscribe on Youtube",
          "href": "https://www.youtube.com/channel/UCRtRQUZMtIua_I7Qu5ZaqOg"
        },
        {
          "text": "Government Jobs",
          "href": "https://allgovernmentjobs.in/latest-government-jobs"
        },
        {
          "text": "Engineering Jobs",
          "href": "https://allgovernmentjobs.in/engineering-jobs"
        },
        {
          "text": "Medical Jobs",
          "href": "https://allgovernmentjobs.in/medical-jobs"
        },
        {
          "text": "Any Degree Jobs",
          "href": "https://allgovernmentjobs.in/any-degree-jobs"
        },
        {
          "text": "Nursing Jobs",
          "href": "https://allgovernmentjobs.in/staff-nurse-jobs"
        },
        {
          "text": "Civil Engineering Jobs",
          "href": "https://allgovernmentjobs.in/civil-engineering-jobs"
        },
        {
          "text": "10th Pass Govt Job",
          "href": "https://allgovernmentjobs.in/10th-pass-govt-jobs"
        },
        {
          "text": "Pharmacist Vacancy",
          "href": "https://allgovernmentjobs.in/pharmacy-jobs"
        },
        {
          "text": "Indian Bank Recruitment 2025 - Apply Offline for Attender Post",
          "href": "https://allgovernmentjobs.in/indian-bank-recruitment-2025-apply-offline-for-attender-post/34255"
        },
        {
          "text": "MRVC Recruitment 2025 - Apply Offline for 04 Project Engineer Posts",
          "href": "https://allgovernmentjobs.in/mrvc-recruitment-2025-apply-offline-for-04-project-engineer-posts/34254"
        },
        {
          "text": "IFGTB Recruitment 2025 - Apply Online for 13 Research Associate and Other Posts",
          "href": "https://allgovernmentjobs.in/ifgtb-recruitment-2025-apply-online-for-13-research-associate-and-other-posts/34253"
        },
        {
          "text": "NIT Trichy Recruitment 2025 - Walk-in-Interview for Junior Research Fellow and Project Associate Post",
          "href": "https://allgovernmentjobs.in/nit-trichy-recruitment-2025-walk-in-interview-for-junior-research-fellow-and-project-associate-post/34252"
        },
        {
          "text": "ICSIL Recruitment 2025 - Apply Online for 02 Project Associate Posts",
          "href": "https://allgovernmentjobs.in/icsil-recruitment-2025-apply-online-for-02-project-associate-posts/34251"
        },
        {
          "text": "RRB Recruitment 2025 - Apply Online for 368 Section Controller Posts",
          "href": "https://allgovernmentjobs.in/rrb-recruitment-2025-apply-online-for-368-section-controller-posts/34250"
        },
        {
          "text": "DHS Cuddalore Recruitment 2025 - Apply Offline 06 Consultant and Other Posts",
          "href": "https://allgovernmentjobs.in/dhs-cuddalore-recruitment-2025-apply-offline-06-consultant-and-other-posts/34249"
        },
        {
          "text": "IB Recruitment 2025 - Apply Online for 394 Junior Intelligent Officer Grade-II Posts",
          "href": "https://allgovernmentjobs.in/ib-recruitment-2025-apply-online-for-394-junior-intelligent-officer-grade-ii-posts/34248"
        },
        {
          "text": "NTPC Recruitment 2025 - Apply Online for 20 Physician Posts",
          "href": "https://allgovernmentjobs.in/ntpc-recruitment-2025-apply-online-for-20-physician-posts/34247"
        },
        {
          "text": "WCD Odisha Recruitment 2025 - Apply Online for 91 Anganwadi Worker & Helper Posts",
          "href": "https://allgovernmentjobs.in/wcd-odisha-recruitment-2025-apply-online-for-91-anganwadi-worker-helper-posts/34246"
        },
        {
          "text": "10th",
          "href": "https://allgovernmentjobs.in/10th-pass-govt-jobs"
        },
        {
          "text": "8th",
          "href": "https://allgovernmentjobs.in/8th-jobs"
        },
        {
          "text": "Aeronautical Engineering",
          "href": "https://allgovernmentjobs.in/aeronautical-engineering-jobs"
        },
        {
          "text": "Agricultural Engineering",
          "href": "https://allgovernmentjobs.in/agricultural-engineering-jobs"
        },
        {
          "text": "ANM",
          "href": "https://allgovernmentjobs.in/anm-jobs"
        },
        {
          "text": "Any Degree",
          "href": "https://allgovernmentjobs.in/any-degree-jobs"
        },
        {
          "text": "Architectural Engineering",
          "href": "https://allgovernmentjobs.in/architectural-engineering-jobs"
        },
        {
          "text": "Automobile Engineering",
          "href": "https://allgovernmentjobs.in/automobile-engineering-jobs"
        },
        {
          "text": "B.E/ B.Tech",
          "href": "https://allgovernmentjobs.in/b-e-b-tech-jobs"
        },
        {
          "text": "B.Ed",
          "href": "https://allgovernmentjobs.in/b-ed-jobs"
        },
        {
          "text": "B.Pharm",
          "href": "https://allgovernmentjobs.in/b-pharm-jobs"
        },
        {
          "text": "B.Sc",
          "href": "https://allgovernmentjobs.in/b-sc-jobs"
        },
        {
          "text": "B.sc Nursing",
          "href": "https://allgovernmentjobs.in/b-sc-nursing-jobs"
        },
        {
          "text": "B.V.Sc",
          "href": "https://allgovernmentjobs.in/b-v-sc-jobs"
        },
        {
          "text": "BAMS",
          "href": "https://allgovernmentjobs.in/bams-jobs"
        },
        {
          "text": "BDS",
          "href": "https://allgovernmentjobs.in/bds-jobs"
        },
        {
          "text": "BHMS",
          "href": "https://allgovernmentjobs.in/bhms-jobs"
        },
        {
          "text": "Biotechnology",
          "href": "https://allgovernmentjobs.in/biotechnology-jobs"
        },
        {
          "text": "BPT",
          "href": "https://allgovernmentjobs.in/bpt-jobs"
        },
        {
          "text": "BUMS",
          "href": "https://allgovernmentjobs.in/bums-jobs"
        },
        {
          "text": "CA/ ICWAI",
          "href": "https://allgovernmentjobs.in/ca-icwa-jobs"
        },
        {
          "text": "Chemical Engineering",
          "href": "https://allgovernmentjobs.in/chemical-engineering-jobs"
        },
        {
          "text": "Civil Engineering",
          "href": "https://allgovernmentjobs.in/civil-engineering-jobs"
        },
        {
          "text": "Computer Science Engineering",
          "href": "https://allgovernmentjobs.in/computer-science-engineering-jobs"
        },
        {
          "text": "D. Pharma",
          "href": "https://allgovernmentjobs.in/d-pharma-jobs-jobs"
        },
        {
          "text": "Diploma",
          "href": "https://allgovernmentjobs.in/diploma-jobs"
        },
        {
          "text": "DMLT",
          "href": "https://allgovernmentjobs.in/dmlt-jobs"
        },
        {
          "text": "DNB",
          "href": "https://allgovernmentjobs.in/dnb-jobs"
        },
        {
          "text": "Electrical and Instrumentation",
          "href": "https://allgovernmentjobs.in/electrical-and-instrumentation-jobs"
        },
        {
          "text": "Electrical Engineering",
          "href": "https://allgovernmentjobs.in/electrical-engineering-jobs"
        },
        {
          "text": "Electronics and Communication Engineering",
          "href": "https://allgovernmentjobs.in/electronics-and-communication-engineering-jobs"
        },
        {
          "text": "Engineering",
          "href": "https://allgovernmentjobs.in/engineering-jobs"
        },
        {
          "text": "GATE",
          "href": "https://allgovernmentjobs.in/gate-jobs"
        },
        {
          "text": "GNM",
          "href": "https://allgovernmentjobs.in/gnm-jobs"
        },
        {
          "text": "Hotel Management",
          "href": "https://allgovernmentjobs.in/hotel-management-jobs"
        },
        {
          "text": "Information Technology",
          "href": "https://allgovernmentjobs.in/information-technology-jobs"
        },
        {
          "text": "Intermediate (10+2)",
          "href": "https://allgovernmentjobs.in/intermediate-10-2-jobs"
        },
        {
          "text": "ITI",
          "href": "https://allgovernmentjobs.in/iti-jobs"
        },
        {
          "text": "LLB",
          "href": "https://allgovernmentjobs.in/llb-jobs"
        },
        {
          "text": "M.A",
          "href": "https://allgovernmentjobs.in/m-a-jobs"
        },
        {
          "text": "M.E / M.Tech",
          "href": "https://allgovernmentjobs.in/m-e-m-tech-jobs"
        },
        {
          "text": "M.Pharm",
          "href": "https://allgovernmentjobs.in/m-pharm-jobs"
        },
        {
          "text": "M.Phil / Ph.D",
          "href": "https://allgovernmentjobs.in/m-phil-ph-d-jobs"
        },
        {
          "text": "M.Sc",
          "href": "https://allgovernmentjobs.in/m-sc-jobs"
        },
        {
          "text": "M.sc Nursing",
          "href": "https://allgovernmentjobs.in/m-sc-nursing-jobs"
        },
        {
          "text": "M.V.Sc",
          "href": "https://allgovernmentjobs.in/m-v-sc-jobs"
        },
        {
          "text": "MBA",
          "href": "https://allgovernmentjobs.in/mba-jobs"
        },
        {
          "text": "MBBS",
          "href": "https://allgovernmentjobs.in/mbbs-jobs"
        },
        {
          "text": "MCA",
          "href": "https://allgovernmentjobs.in/mca-jobs"
        },
        {
          "text": "MDS",
          "href": "https://allgovernmentjobs.in/mds-jobs"
        },
        {
          "text": "Mechanical Engineering",
          "href": "https://allgovernmentjobs.in/mechanical-engineering-jobs"
        },
        {
          "text": "Medical",
          "href": "https://allgovernmentjobs.in/medical-jobs"
        },
        {
          "text": "Mining Engineering",
          "href": "https://allgovernmentjobs.in/mining-engineering-jobs"
        },
        {
          "text": "MS/ MD",
          "href": "https://allgovernmentjobs.in/ms-md-jobs"
        },
        {
          "text": "Petroleum Engineering",
          "href": "https://allgovernmentjobs.in/petroleum-engineering-jobs"
        },
        {
          "text": "PGDM",
          "href": "https://allgovernmentjobs.in/pgdm-jobs"
        },
        {
          "text": "Pharm D",
          "href": "https://allgovernmentjobs.in/pharm-d-jobs"
        },
        {
          "text": "Pharmacy",
          "href": "https://allgovernmentjobs.in/pharmacy-jobs"
        },
        {
          "text": "Post Graduation",
          "href": "https://allgovernmentjobs.in/post-graduation-jobs"
        },
        {
          "text": "Sports Quota",
          "href": "https://allgovernmentjobs.in/sports-quota-jobs"
        },
        {
          "text": "Staff Nurse",
          "href": "https://allgovernmentjobs.in/staff-nurse-jobs"
        },
        {
          "text": "Register",
          "href": "https://allgovernmentjobs.in/register"
        },
        {
          "text": "Login",
          "href": "https://allgovernmentjobs.in/login"
        },
        {
          "text": "About Us",
          "href": "https://allgovernmentjobs.in/about-us"
        },
        {
          "text": "Contact Us",
          "href": "https://allgovernmentjobs.in/contact-us"
        },
        {
          "text": "Careers",
          "href": "https://allgovernmentjobs.in/careers"
        },
        {
          "text": "Terms & Conditions",
          "href": "https://allgovernmentjobs.in/terms-and-conditions"
        },
        {
          "text": "Privacy Policy",
          "href": "https://allgovernmentjobs.in/privacy-policy"
        },
        {
          "text": "Sitemap",
          "href": "https://allgovernmentjobs.in/sitemap"
        },
        {
          "text": "Subscribe",
          "href": "https://allgovernmentjobs.in/register"
        },
        {
          "text": "Government Jobs",
          "href": "https://allgovernmentjobs.in/latest-government-jobs"
        },
        {
          "text": "Employment News",
          "href": "https://allgovernmentjobs.in/employment-news"
        },
        {
          "text": "Free Job Alert",
          "href": "https://allgovernmentjobs.in/free-job-alert"
        },
        {
          "text": "State Government Jobs",
          "href": "https://allgovernmentjobs.in/state-government-jobs"
        },
        {
          "text": "Central Government Jobs",
          "href": "https://allgovernmentjobs.in/central-government-jobs"
        },
        {
          "text": "Govt Jobs by Education",
          "href": "https://allgovernmentjobs.in/jobs-by-qualification"
        },
        {
          "text": "Govt Jobs by Organisation",
          "href": "https://allgovernmentjobs.in/jobs-by-organization"
        },
        {
          "text": "Govt Jobs by Roles",
          "href": "https://allgovernmentjobs.in/"
        },
        {
          "text": "Govt Jobs by Location",
          "href": "https://allgovernmentjobs.in/"
        },
        {
          "text": "Previous Papers",
          "href": "https://allgovernmentjobs.in/previous-papers"
        },
        {
          "text": "Results",
          "href": "https://allgovernmentjobs.in/results"
        },
        {
          "text": "Admit Card",
          "href": "https://allgovernmentjobs.in/admit-cards"
        },
        {
          "text": "Answer Keys",
          "href": "https://allgovernmentjobs.in/answer-key"
        },
        {
          "text": "Syllabus",
          "href": "https://allgovernmentjobs.in/syllabus"
        }
      ],
      "sections": {
        "eligibility": [
          "Name of the PostsVacanciesEducationAssistant Level-4 & Level-250Diploma in Electrical, Mechanical Engineering, 10th pass, ITI",
          "MIDHANI Recruitment 2025 Age Limit:",
          "The minimum age limit: 18 Years.The maximum age limit: 35 Years.Age relaxation is based on the Organisation's norms.",
          "MIDHANI Recruitment 2025 Selection Process:",
          "The selection process is based on the interview."
        ],
        "qualification": [
          "10th8thAeronautical EngineeringAgricultural EngineeringANMAny DegreeArchitectural EngineeringAutomobile EngineeringB.E/ B.TechB.EdB.PharmB.ScB.sc NursingB.V.ScBAMSBDSBHMSBiotechnologyBPTBUMSCA/ ICWAIChemical EngineeringCivil EngineeringComputer Science EngineeringD. PharmaDiplomaDMLTDNBElectrical and InstrumentationElectrical EngineeringElectronics and Communication EngineeringEngineeringGATEGNMHotel ManagementInformation TechnologyIntermediate (10+2)ITILLBM.AM.E / M.TechM.PharmM.Phil / Ph.DM.ScM.sc NursingM.V.ScMBAMBBSMCAMDSMechanical EngineeringMedicalMining EngineeringMS/ MDPetroleum EngineeringPGDMPharm DPharmacyPost GraduationSports QuotaStaff Nurse"
        ],
        "how_to apply": [
          "Go to the official website.Visit the MIDHANI Recruitment 2025 notification.Read the instructions carefully and check the eligiblity criteria.If you are eligible.Gather all the required documents.Carry all the documents to the interview.Attend the interview at the mentioned address.",
          "Address:",
          "MIDHANI Corporate Office Auditorium, Kanchanbagh, Hyderabad – 500 058.",
          "Important Dates:",
          "Starting date21-08-2025Closing date17-09-2025"
        ]
      }
    }
  }
}