{
  "id": "df311d77-8038-4a5a-80a8-d073e4c0126f",
  "url": "https://allgovernmentjobs.in/dhs-karur-recruitment-2025-apply-offline-for-87-staff-nurse-and-other-posts/33773",
  "title": "Staff Nurse",
  "organization": "DHS Karur",
  "department": null,
  "location": "Punjab",
  "positions": [
    {
      "title": "Staff Nurse",
      "vacancies": 62,
      "qualification": "GNM, B.Sc Nursing"
    },
    {
      "title": "Lab Technician",
      "vacancies": 5,
      "qualification": "Diploma, DMLT, 12th"
    },
    {
      "title": "MMU Cleaner",
      "vacancies": 1,
      "qualification": "08th"
    },
    {
      "title": "Hospital Worker",
      "vacancies": 4,
      "qualification": null
    },
    {
      "title": "Psychologist",
      "vacancies": 1,
      "qualification": "M.Sc., M.A."
    },
    {
      "title": "Social Worker",
      "vacancies": 5,
      "qualification": "M.A"
    },
    {
      "title": "Security",
      "vacancies": 2,
      "qualification": "08th"
    },
    {
      "title": "Radiographer",
      "vacancies": 5,
      "qualification": "Diploma, B.Sc"
    },
    {
      "title": "Pharmacist",
      "vacancies": 2,
      "qualification": "D. Pharm"
    }
  ],
  "totalPosts": 87,
  "qualification": "details, age limit, selection process, application fee, salary, and how to apply for these posts before the deadline",
  "salary": "₹8,500",
  "applicationStartDate": "2025-07-25",
  "lastDate": "2025-08-14",
  "postedDate": "2025-08-11T22:12:42.087Z",
  "links": {
    "official": null,
    "notification": null,
    "applicationForm": "https://files.allgovernmentjobs.in/public/2025/07/1753875666d19a80d6ebd94669c0df30e92f1079ab907520ec.pdf",
    "sourceUrl": "https://allgovernmentjobs.in/dhs-karur-recruitment-2025-apply-offline-for-87-staff-nurse-and-other-posts/33773",
    "applicationFormLocal": "/data/application_forms/df311d77-8038-4a5a-80a8-d073e4c0126f_form.pdf"
  },
  "metadata": {
    "scrapedAt": "2025-08-11T22:12:42.087Z",
    "processedAt": "2025-08-12T18:25:34.910Z"
  }
}